{
	"attacks":{
		"normal":{
			"attack":"Botta",
			"sattack":"Graffio"
		},
		"fire":{
			"attack":"Fuocopugno",
			"sattack":"Lanciafiamme"
		},
		"grass":{
			"attack":"Frustata",
			"sattack":"Solarraggio"
		},
		"water":{
			"attack":"Pistolacqua",
			"sattack":"Idropompa"
		},
		"ice":{
			"attack":"Geloraggio",
			"sattack":"Grandine"
		},
		"electric":{
			"attack":"Fulmine",
			"sattack":"Scarica"
		},
		"fighting":{
			"attack":"Doppiocalcio",
			"sattack":"Incrocolpo"
		},
		"flying":{
			"attack":"Raffica",
			"sattack":"Attacco D'Ala"
		},
		"bug":{
			"attack":"Millebave",
			"sattack":"Missilspillo"
		},
		"ghost":{
			"attack":"Incubo",
			"sattack":"Palla Ombra"
		},
		"rock":{
			"attack":"",
			"sattack":""
		},
		"ground":{
			"attack":"",
			"sattack":""
		},
		"steel":{
			"attack":"",
			"sattack":""
		},
		"dark":{
			"attack":"",
			"sattack":""
		},
		"psychic":{
			"attack":"",
			"sattack":""
		},
		"fairy":{
			"attack":"",
			"sattack":""
		},
		"dragon":{
			"attack":"",
			"sattack":""
		},
		"poison":{
			"attack":"",
			"sattack":""
		}
	}
	"players":{
		"niccolò":{
		    "name":"Niccolò",
		    "pokemons":"➤130-Gyarados<br>➤405-Luxray<br>➤374-Beldum<br>➤626-Bouffalant<br>➤529-Drilbur<br>➤344-Claydol<br>➤621-Druddigon<br>➤527-Woobat<br>➤150-Mew Two<br>➤646-Kyurem<br>➤663-Talonflame<br>➤601-Klinklang<br>"
		},
		"gabriele":{
		    "name":"Gabriele",
		    "pokemons":"➤6-Charizard<br>➤553-Krokodile<br>➤579-Reuniclus<br>➤742-Cutiefly<br>➤334-Altaria<br>➤37-Vulpix<br>➤675-Pangoro<br>"
		},
		"davide":{
			"name":"Davide",
			"pokemons":"➤6-Charizard<br>➤561-Sigilyph<br>➤799-Guzzlord<br>➤200-Misdreavus<br>➤263-Zigzagoon<br>➤280-Ralts<br>"
		},
		"caterina":{
			"name":"Caterina",
			"pokemons":"➤130-Gyarados<br>➤540-Sewaddle<br>➤339-Barboach<br>➤277-Swellow<br>➤9-Blastoise<br>➤712-Bergmite<br>"
		}
	}
}
